src/__init__.py
src/umps222.py
umps222-0.1.1.dist-info/METADATA
umps222-0.1.1.dist-info/WHEEL
umps222-0.1.1.dist-info/entry_points.txt
umps222-0.1.1.dist-info/top_level.txt
umps222-0.1.1.dist-info/RECORD
