Metadata-Version: 2.1
Name: umps222
Version: 0.1.1
Summary: upms tool
Author: maoxiangdong
Author-email: xx@gmail.com
Classifier: Development Status :: 4 - Beta
Classifier: License :: OSI Approved :: MIT License
Classifier: Programming Language :: Python :: 3.10
Classifier: Programming Language :: Python :: 3.9
Classifier: Programming Language :: Python :: 3.8
Requires-Dist: Scons
